Gormley_PETRAFT/Synthesis_scriptor.py
Gormley_PETRAFT/__init__.py
gormley_petraft-0.1.0.dist-info/METADATA
gormley_petraft-0.1.0.dist-info/WHEEL
gormley_petraft-0.1.0.dist-info/entry_points.txt
gormley_petraft-0.1.0.dist-info/top_level.txt
gormley_petraft-0.1.0.dist-info/RECORD
