Metadata-Version: 2.4
Name: Gormley_PETRAFT
Version: 0.1.0
Summary: Automated ATRP recipe generator for PET-RAFT synthesis
Author: Your Name
Requires-Python: >=3.7
Requires-Dist: pandas>=1.3.0
Requires-Dist: openpyxl
Dynamic: author
Dynamic: description-content-type
Dynamic: requires-dist
Dynamic: requires-python
Dynamic: summary
